simepy/__init__.py
simepy/extract_meta_data.py
simepy/extract_scans.py
simepy-0.3.2.dist-info/METADATA
simepy-0.3.2.dist-info/WHEEL
simepy-0.3.2.dist-info/RECORD
