Metadata-Version: 2.1
Name: simepy
Version: 0.3.2
Summary: 
Author: Gavain Sweetman, Manuel Kösters, Artyom Vlasov, Tristan Ranff, Christian Fufezan
Requires-Python: >=3.8,<4.0
Classifier: Programming Language :: Python :: 3
Classifier: Programming Language :: Python :: 3.8
Classifier: Programming Language :: Python :: 3.9
Classifier: Programming Language :: Python :: 3.10
Classifier: Programming Language :: Python :: 3.11
Requires-Dist: pandas (>=2.0,<2.1)
Requires-Dist: pydantic (>=1.10.7,<3.0.0)
Requires-Dist: pymzml (==2.5.2)
